MANIFEST.in
VERSION
distribute_setup.py
setup.py
src/urecord.py
src/urecord.egg-info/PKG-INFO
src/urecord.egg-info/SOURCES.txt
src/urecord.egg-info/dependency_links.txt
src/urecord.egg-info/top_level.txt