Metadata-Version: 1.0
Name: urecord
Version: 0.0.4
Summary: A structured record metaclass.
Home-page: http://github.com/zacharyvoase/urecord
Author: Zachary Voase
Author-email: z@zacharyvoase.com
License: UNKNOWN
Platform: UNKNOWN
